strufi/__init__.py
strufi/dump_primitives.py
strufi/exceptions.py
strufi/load_primitives.py
strufi/py.typed
strufi/reader.py
strufi/types.py
strufi-1.0.1.dist-info/licenses/LICENSE
strufi-1.0.1.dist-info/METADATA
strufi-1.0.1.dist-info/WHEEL
strufi-1.0.1.dist-info/top_level.txt
strufi-1.0.1.dist-info/RECORD
