Metadata-Version: 2.4
Name: strufi
Version: 1.0.1
Summary: Parser for HTTP Structured Field Values
Author-email: Alma Engineering <engineering@almapay.com>
License-Expression: MIT
Project-URL: homepage, https://github.com/alma/strufi
Project-URL: changelog, https://github.com/alma/strufi/blob/main/CHANGELOG.md
Keywords: HTTP,Structured Field Values,RFC 8941,RFC 9651
Classifier: Development Status :: 5 - Production/Stable
Classifier: Intended Audience :: Developers
Classifier: Programming Language :: Python :: 3
Classifier: Programming Language :: Python :: 3 :: Only
Classifier: Programming Language :: Python :: 3.12
Classifier: Programming Language :: Python :: 3.13
Classifier: Topic :: Internet :: WWW/HTTP
Classifier: Topic :: Software Development :: Libraries :: Python Modules
Requires-Python: >=3.12
License-File: LICENSE
Provides-Extra: dev
Requires-Dist: pytest; extra == "dev"
Requires-Dist: ruff; extra == "dev"
Requires-Dist: mypy; extra == "dev"
Provides-Extra: build
Requires-Dist: build; extra == "build"
Requires-Dist: twine; extra == "build"
Dynamic: license-file
